5_fullAdder/full_adder.v
/*
+-----+-----+-----+-------+-------------+
|  A  |  B  | Cin |  S    | C_out       |
+-----+-----+-----+-------+-------------+
|  0  |  0  |  0  |   0   |     0       |
+-----+-----+-----+-------+-------------+
|  0  |  0  |  1  |   1   |     0       |
+-----+-----+-----+-------+-------------+
|  0  |  1  |  0  |   1   |     0       |
+-----+-----+-----+-------+-------------+
|  0  |  1  |  1  |   0   |     1       |
+-----+-----+-----+-------+-------------+
|  1  |  0  |  0  |   1   |     0       |
+-----+-----+-----+-------+-------------+
|  1  |  0  |  1  |   0   |     1       |
+-----+-----+-----+-------+-------------+
|  1  |  1  |  0  |   0   |     1       |
+-----+-----+-----+-------+-------------+
|  1  |  1  |  1  |   1   |     1       |
+-----+-----+-----+-------+-------------+

sum = a^b^c
cout = (a&b) | (a&c) | (b&c)
*/

module full_adder(input a, b, cin, output sum, cout);
	assign sum 	= a^b^cin;
	assign cout	= (a&b) | (a&cin) | (b&cin);
endmodule

5_fullAdder/tb_full_adder.v
module tb_full_adder();
	reg 	A, B, Cin;	
	wire	Sum, C_out;

	full_adder uut(
		.a(A),
		.b(B),
		.cin(Cin),
		.sum(Sum),
		.cout(C_out)
	);

	initial begin 
		$dumpfile("waveform.vcd");
		$dumpvars(0, tb_full_adder);

		$monitor("A = %b, B = %b, Cin = %b, Sum = %b, Carry = %b", A, B, Cin, Sum, C_out);

        	// Kiểm tra tất cả các kết hợp giá trị của A, B, Cin
        	A = 0; B = 0; Cin = 0; #10;  // Test 000
        	A = 0; B = 0; Cin = 1; #10;  // Test 001
        	A = 0; B = 1; Cin = 0; #10;  // Test 010
        	A = 0; B = 1; Cin = 1; #10;  // Test 011
        	A = 1; B = 0; Cin = 0; #10;  // Test 100
        	A = 1; B = 0; Cin = 1; #10;  // Test 101
        	A = 1; B = 1; Cin = 0; #10;  // Test 110
        	A = 1; B = 1; Cin = 1; #10;  // Test 111

        	$finish;  // Kết thúc mô phỏng
	end
endmodule

5_fullAdder/waveform.vcd
$date
	Sun Aug 31 05:53:55 2025
$end
$version
	Icarus Verilog
$end
$timescale
	1s
$end
$scope module tb_full_adder $end
$var wire 1 ! Sum $end
$var wire 1 " C_out $end
$var reg 1 # A $end
$var reg 1 $ B $end
$var reg 1 % Cin $end
$scope module uut $end
$var wire 1 # a $end
$var wire 1 $ b $end
$var wire 1 % cin $end
$var wire 1 " cout $end
$var wire 1 ! sum $end
$upscope $end
$upscope $end
$enddefinitions $end
$comment Show the parameter values. $end
$dumpall
$end
#0
$dumpvars
0%
0$
0#
0"
0!
$end
#10
1!
1%
#20
0%
1$
#30
1"
0!
1%
#40
0"
1!
0%
0$
1#
#50
1"
0!
1%
#60
0%
1$
#70
1!
1%
