4_fullAdderUsinghalfAdder/half_adder.v
/*
+-----+-----+-----+-------+
|  A  |  B  | Sum | Carry |
+-----+-----+-----+-------+
|  0  |  0  |  0  |   0   |
+-----+-----+-----+-------+
|  0  |  1  |  1  |   0   |
+-----+-----+-----+-------+
|  1  |  0  |  1  |   0   |
+-----+-----+-----+-------+
|  1  |  1  |  0  |   1   |
+-----+-----+-----+-------+

sum 	= 1 khi (a = 0 va b = 1) va (a = 1 va b = 0) => a'.b + a.b' = a^b (a xor b)
cout 	= 1 khi (a = 1 va b = 1) => a&b (a and b)

*/



module half_adder(a, b, sum, cout);

	input 		a, b;
	output 		sum, cout;

	assign sum 	= a ^ b;
	assign cout 	= a & b; 

endmodule

4_fullAdderUsinghalfAdder/full_adder.v
/*
+-----+-----+-----+-------+-------------+
|  A  |  B  | Cin |  S    | C_out       |
+-----+-----+-----+-------+-------------+
|  0  |  0  |  0  |   0   |     0       |
+-----+-----+-----+-------+-------------+
|  0  |  0  |  1  |   1   |     0       |
+-----+-----+-----+-------+-------------+
|  0  |  1  |  0  |   1   |     0       |
+-----+-----+-----+-------+-------------+
|  0  |  1  |  1  |   0   |     1       |
+-----+-----+-----+-------+-------------+
|  1  |  0  |  0  |   1   |     0       |
+-----+-----+-----+-------+-------------+
|  1  |  0  |  1  |   0   |     1       |
+-----+-----+-----+-------+-------------+
|  1  |  1  |  0  |   0   |     1       |
+-----+-----+-----+-------+-------------+
|  1  |  1  |  1  |   1   |     1       |
+-----+-----+-----+-------+-------------+

sum = a^b^c
cout = (a&b) + ((a^b)&c)
*/

module full_adder(input a, b, cin, output sum, cout);
    
    wire s1,c1,c2;

    half_adder ha1(a, b, s1, c1);
    half_adder ha2(s1, cin, sum, c2);

    assign cout = c1|c2;
endmodule

4_fullAdderUsinghalfAdder/tb_full_adder.v
module tb_full_adder;
    reg A, B, Cin;      
    wire Sum, C_out;    

    full_adder uut (
        .a(A),
        .b(B),
        .cin(Cin),
        .sum(Sum),
        .cout(C_out)
    );

    initial begin

        $dumpfile("waveform.vcd");
        $dumpvars(0, tb_full_adder);
        // Đảm bảo rằng mọi tín hiệu được in ra khi có sự thay đổi
        $monitor("A = %b, B = %b, Cin = %b, Sum = %b, Carry = %b", A, B, Cin, Sum, C_out);

        // Kiểm tra tất cả các kết hợp giá trị của A, B, Cin
        A = 0; B = 0; Cin = 0; #10;  // Test 000
        A = 0; B = 0; Cin = 1; #10;  // Test 001
        A = 0; B = 1; Cin = 0; #10;  // Test 010
        A = 0; B = 1; Cin = 1; #10;  // Test 011
        A = 1; B = 0; Cin = 0; #10;  // Test 100
        A = 1; B = 0; Cin = 1; #10;  // Test 101
        A = 1; B = 1; Cin = 0; #10;  // Test 110
        A = 1; B = 1; Cin = 1; #10;  // Test 111

        $finish;  // Kết thúc mô phỏng
    end
endmodule

4_fullAdderUsinghalfAdder/waveform.vcd
$date
	Sat Aug 30 22:49:17 2025
$end
$version
	Icarus Verilog
$end
$timescale
	1s
$end
$scope module tb_full_adder $end
$var wire 1 ! Sum $end
$var wire 1 " C_out $end
$var reg 1 # A $end
$var reg 1 $ B $end
$var reg 1 % Cin $end
$scope module uut $end
$var wire 1 # a $end
$var wire 1 $ b $end
$var wire 1 % cin $end
$var wire 1 " cout $end
$var wire 1 ! sum $end
$var wire 1 & s1 $end
$var wire 1 ' c2 $end
$var wire 1 ( c1 $end
$scope module ha1 $end
$var wire 1 # a $end
$var wire 1 $ b $end
$var wire 1 ( cout $end
$var wire 1 & sum $end
$upscope $end
$scope module ha2 $end
$var wire 1 & a $end
$var wire 1 % b $end
$var wire 1 ' cout $end
$var wire 1 ! sum $end
$upscope $end
$upscope $end
$upscope $end
$enddefinitions $end
$comment Show the parameter values. $end
$dumpall
$end
#0
$dumpvars
0(
0'
0&
0%
0$
0#
0"
0!
$end
#10
1!
1%
#20
1&
0%
1$
#30
1"
0!
1'
1%
#40
0"
1!
0'
0%
0$
1#
#50
1"
0!
1'
1%
#60
0'
0&
1(
0%
1$
#70
1!
1%
