7_fullSubtractor/full_subtractor.v
/*
| A | B | Bin | D | Borrow |
|---|---|-----|---|--------|
| 0 | 0 |  0  | 0 |   0    |
| 0 | 0 |  1  | 1 |   1    |
| 0 | 1 |  0  | 1 |   1    |
| 0 | 1 |  1  | 0 |   1    |
| 1 | 0 |  0  | 1 |   0    |
| 1 | 0 |  1  | 0 |   0    |
| 1 | 1 |  0  | 0 |   0    |
| 1 | 1 |  1  | 1 |   1    |

d = a^b^bin
borrow = (~a&b) | (bin&~a) | (bin&b) 
*/
module full_subtractor(input a, b, bin, output d, borrow);
	assign d = a^b^bin;
	assign borrow = (~a&b) | (bin&~a) | (bin&b);
endmodule

7_fullSubtractor/tb_full_subtractor.v
module tb_full_subtractor;

    reg a, b, bin;
    wire d, borrow;

    full_subtractor uut (
        .a(a),
        .b(b),
        .bin(bin),
        .d(d),
        .borrow(borrow)
    );

    initial begin
        	
	$dumpfile("wave_form.vcd");
	$dumpvars(0, tb_full_subtractor);	

	$display("A B Bin | D Borrow");
        $display("-------|----------");
        for (integer i = 0; i < 8; i = i + 1) begin
            {a, b, bin} = i[2:0];
            #1; // delay nhỏ để cập nhật output
            $display("%b %b  %b  | %b   %b", a, b, bin, d, borrow);
        end
        $finish;
    end

endmodule

7_fullSubtractor/wave_form.vcd
$date
	Tue Sep  2 22:28:20 2025
$end
$version
	Icarus Verilog
$end
$timescale
	1s
$end
$scope module tb_full_subtractor $end
$var wire 1 ! d $end
$var wire 1 " borrow $end
$var reg 1 # a $end
$var reg 1 $ b $end
$var reg 1 % bin $end
$scope module uut $end
$var wire 1 # a $end
$var wire 1 $ b $end
$var wire 1 % bin $end
$var wire 1 " borrow $end
$var wire 1 ! d $end
$upscope $end
$scope begin $ivl_for_loop0 $end
$var integer 32 & i [31:0] $end
$upscope $end
$upscope $end
$enddefinitions $end
$comment Show the parameter values. $end
$dumpall
$end
#0
$dumpvars
b0 &
0%
0$
0#
0"
0!
$end
#1
1"
1!
1%
b1 &
#2
1!
1$
0%
b10 &
#3
0!
1%
b11 &
#4
0"
1!
1#
0$
0%
b100 &
#5
0!
1%
b101 &
#6
0!
1$
0%
b110 &
#7
1"
1!
1%
b111 &
#8
b1000 &
