8_fullSubtractorUsingHalfSubtractor/half_subtractor.v
/*
+-----+-----+-----+-------+
|  A  |  B  | diff| borrow|
+-----+-----+-----+-------+
|  0  |  0  |  0  |   0   |
+-----+-----+-----+-------+
|  0  |  1  |  1  |   1   |
+-----+-----+-----+-------+
|  1  |  0  |  1  |   0   |
+-----+-----+-----+-------+
|  1  |  1  |  0  |   0   |
+-----+-----+-----+-------+

diff    = 1 khi (a = 0 va b = 1) va (a = 1 va b = 0)
=> a'.b + a.b' = a^b (a xor b)

borrow  = 1 khi (a = 0 va b = 1)
=> (~a)&b (~a and b)

*/

module half_subtractor(input a, b, output d, bo);
        assign d     = a^b;
        assign bo   = (~a)&b;
endmodule

8_fullSubtractorUsingHalfSubtractor/full_subtractor.v
module full_subtractor(input a, b, bi, output d, bo);

	wire w1, w2, w3;

	half_subtractor hs1(a, b, w1, w2);
	half_subtractor hs2(w1, bi, d, w3);

	assign bo = w2|w3;
endmodule

8_fullSubtractorUsingHalfSubtractor/tb_full_subtractor.v
module tb_full_subtractor();
	reg a,b,bi; 
	wire d,bo;

	full_subtractor uut(
		.a(a),
		.b(b),
		.bi(bi),
		.d(d),
		.bo(bo)
	);

	initial	begin
		$dumpfile("wave_form.vcd");
		$dumpvars(0, tb_full_subtractor);

		a=0;b=0;bi=0; #10
		a=0;b=0;bi=1; #10
		a=0;b=1;bi=0; #10
		a=0;b=1;bi=1; #10
		a=1;b=0;bi=0; #10
		a=1;b=0;bi=1; #10
		a=1;b=1;bi=0; #10
		a=1;b=1;bi=1; #10
		$finish;
	end
endmodule

8_fullSubtractorUsingHalfSubtractor/wave_form.vcd
$date
	Wed Sep  3 18:53:35 2025
$end
$version
	Icarus Verilog
$end
$timescale
	1s
$end
$scope module tb_full_subtractor $end
$var wire 1 ! d $end
$var wire 1 " bo $end
$var reg 1 # a $end
$var reg 1 $ b $end
$var reg 1 % bi $end
$scope module uut $end
$var wire 1 # a $end
$var wire 1 $ b $end
$var wire 1 % bi $end
$var wire 1 " bo $end
$var wire 1 & w3 $end
$var wire 1 ' w2 $end
$var wire 1 ( w1 $end
$var wire 1 ! d $end
$scope module hs1 $end
$var wire 1 # a $end
$var wire 1 $ b $end
$var wire 1 ' bo $end
$var wire 1 ( d $end
$upscope $end
$scope module hs2 $end
$var wire 1 ( a $end
$var wire 1 % b $end
$var wire 1 & bo $end
$var wire 1 ! d $end
$upscope $end
$upscope $end
$upscope $end
$enddefinitions $end
$comment Show the parameter values. $end
$dumpall
$end
#0
$dumpvars
0(
0'
0&
0%
0$
0#
0"
0!
$end
#10
1"
1!
1&
1%
#20
0&
1(
1'
0%
1$
#30
0!
1%
#40
0"
1!
0'
0%
0$
1#
#50
0!
1%
#60
0(
0%
1$
#70
1"
1!
1&
1%
